LICENSE.txt
MANIFEST.in
README.rst
setup.py
docs/Makefile
docs/conf.py
docs/index.rst
nonstdlib/__init__.py
nonstdlib/approx.py
nonstdlib/cast.py
nonstdlib/debug.py
nonstdlib/fmt.py
nonstdlib/io.py
nonstdlib/meta.py
nonstdlib/misc.py
nonstdlib/proc.py
nonstdlib/sci.py
nonstdlib/text.py
nonstdlib.egg-info/PKG-INFO
nonstdlib.egg-info/SOURCES.txt
nonstdlib.egg-info/dependency_links.txt
nonstdlib.egg-info/not-zip-safe
nonstdlib.egg-info/requires.txt
nonstdlib.egg-info/top_level.txt
tests/.coverage
tests/.coveragerc
tests/.gitignore
tests/10_test_debug.py
tests/20_test_io.py
tests/30_test_approx.py
tests/40_test_fmt.py
tests/50_test_sci.py
tests/60_test_misc.py
tests/70_test_text.py
tests/80_test_cast.py
tests/90_test_meta.py
tests/pytest.ini
tests/.cache/v/cache/lastfailed
tests/.pytest_cache/README.md
tests/.pytest_cache/v/cache/lastfailed
tests/.pytest_cache/v/cache/nodeids
tests/htmlcov/_home_kale__local_lib_python3_4_site-packages_nonstdlib___init__.html
tests/htmlcov/_home_kale__local_lib_python3_4_site-packages_nonstdlib_debug.html
tests/htmlcov/_home_kale__local_lib_python3_4_site-packages_nonstdlib_io.html
tests/htmlcov/_home_kale__local_lib_python3_4_site-packages_nonstdlib_meta.html
tests/htmlcov/_home_kale__local_lib_python3_4_site-packages_nonstdlib_misc.html
tests/htmlcov/_home_kale__local_lib_python3_4_site-packages_nonstdlib_text.html
tests/htmlcov/_home_kale_hacking_libraries_nonstdlib_env_lib_python3_4_site-packages_nonstdlib___init___py.html
tests/htmlcov/_home_kale_hacking_libraries_nonstdlib_env_lib_python3_4_site-packages_nonstdlib_approx_py.html
tests/htmlcov/_home_kale_hacking_libraries_nonstdlib_env_lib_python3_4_site-packages_nonstdlib_debug_py.html
tests/htmlcov/_home_kale_hacking_libraries_nonstdlib_env_lib_python3_4_site-packages_nonstdlib_io_py.html
tests/htmlcov/_home_kale_hacking_libraries_nonstdlib_env_lib_python3_4_site-packages_nonstdlib_meta_py.html
tests/htmlcov/_home_kale_hacking_libraries_nonstdlib_env_lib_python3_4_site-packages_nonstdlib_misc_py.html
tests/htmlcov/_home_kale_hacking_libraries_nonstdlib_env_lib_python3_4_site-packages_nonstdlib_text_py.html
