Metadata-Version: 1.1
Name: nonstdlib
Version: 1.11.0
Summary: A collection of general-purpose utilities
Home-page: https://github.com/kalekundert/nonstdlib
Author: Kale Kundert
Author-email: kale@thekunderts.net
License: MIT
Keywords: nonstdlib
Platform: UNKNOWN
Classifier: Development Status :: 2 - Pre-Alpha
Classifier: Intended Audience :: Developers
Classifier: License :: OSI Approved :: MIT License
Classifier: Natural Language :: English
Classifier: Programming Language :: Python :: 3
Classifier: Topic :: Software Development :: Libraries
